{
  "metadata": {
    "environment": "CartPole-v1",
    "total_episodes": 480,
    "best_average_reward": 500.0,
    "final_100_avg": 500.0,
    "training_time_seconds": 30.845369338989258,
    "action_type": "Discrete",
    "state_dim": 4,
    "action_dim": 2,
    "checkpoint": "results\\ablation\\CartPole-v1\\baseline\\best_baseline_seed1.pth",
    "seed": 1,
    "run_name": "baseline_seed1"
  },
  "rewards": [
    22.0,
    16.0,
    23.0,
    14.0,
    23.0,
    37.0,
    17.0,
    29.0,
    18.0,
    16.0,
    19.0,
    29.0,
    14.0,
    11.0,
    8.0,
    18.0,
    21.0,
    24.0,
    39.0,
    20.0,
    18.0,
    22.0,
    12.0,
    12.0,
    14.0,
    16.0,
    13.0,
    14.0,
    17.0,
    27.0,
    11.0,
    16.0,
    18.0,
    13.0,
    19.0,
    32.0,
    24.0,
    11.0,
    39.0,
    19.0,
    15.0,
    28.0,
    19.0,
    20.0,
    12.0,
    18.0,
    17.0,
    25.0,
    24.0,
    22.0,
    14.0,
    13.0,
    9.0,
    37.0,
    16.0,
    11.0,
    12.0,
    45.0,
    19.0,
    17.0,
    27.0,
    24.0,
    23.0,
    15.0,
    20.0,
    14.0,
    19.0,
    13.0,
    83.0,
    18.0,
    16.0,
    33.0,
    24.0,
    24.0,
    10.0,
    18.0,
    48.0,
    15.0,
    31.0,
    15.0,
    14.0,
    26.0,
    11.0,
    16.0,
    30.0,
    17.0,
    12.0,
    16.0,
    30.0,
    10.0,
    19.0,
    21.0,
    12.0,
    35.0,
    22.0,
    42.0,
    13.0,
    35.0,
    39.0,
    35.0,
    43.0,
    21.0,
    16.0,
    17.0,
    12.0,
    32.0,
    16.0,
    15.0,
    46.0,
    17.0,
    31.0,
    20.0,
    16.0,
    43.0,
    22.0,
    29.0,
    14.0,
    24.0,
    15.0,
    16.0,
    22.0,
    12.0,
    49.0,
    13.0,
    17.0,
    20.0,
    16.0,
    32.0,
    18.0,
    37.0,
    23.0,
    13.0,
    15.0,
    44.0,
    16.0,
    12.0,
    14.0,
    23.0,
    14.0,
    11.0,
    18.0,
    39.0,
    35.0,
    21.0,
    22.0,
    39.0,
    42.0,
    26.0,
    61.0,
    32.0,
    100.0,
    18.0,
    52.0,
    15.0,
    25.0,
    28.0,
    35.0,
    63.0,
    21.0,
    19.0,
    29.0,
    29.0,
    21.0,
    27.0,
    23.0,
    15.0,
    10.0,
    33.0,
    12.0,
    38.0,
    22.0,
    36.0,
    20.0,
    53.0,
    67.0,
    47.0,
    22.0,
    16.0,
    34.0,
    106.0,
    31.0,
    19.0,
    58.0,
    37.0,
    108.0,
    63.0,
    25.0,
    17.0,
    14.0,
    31.0,
    17.0,
    26.0,
    62.0,
    28.0,
    71.0,
    18.0,
    12.0,
    17.0,
    35.0,
    17.0,
    84.0,
    70.0,
    25.0,
    78.0,
    31.0,
    19.0,
    28.0,
    24.0,
    84.0,
    22.0,
    103.0,
    13.0,
    20.0,
    17.0,
    39.0,
    143.0,
    55.0,
    23.0,
    12.0,
    76.0,
    30.0,
    35.0,
    26.0,
    19.0,
    80.0,
    28.0,
    37.0,
    147.0,
    40.0,
    30.0,
    98.0,
    47.0,
    29.0,
    26.0,
    75.0,
    28.0,
    72.0,
    116.0,
    64.0,
    30.0,
    45.0,
    66.0,
    58.0,
    22.0,
    99.0,
    62.0,
    50.0,
    13.0,
    64.0,
    53.0,
    59.0,
    15.0,
    58.0,
    76.0,
    44.0,
    31.0,
    90.0,
    63.0,
    34.0,
    14.0,
    150.0,
    237.0,
    102.0,
    117.0,
    83.0,
    129.0,
    110.0,
    209.0,
    128.0,
    187.0,
    60.0,
    76.0,
    117.0,
    27.0,
    118.0,
    158.0,
    199.0,
    290.0,
    106.0,
    74.0,
    142.0,
    240.0,
    65.0,
    185.0,
    105.0,
    195.0,
    179.0,
    135.0,
    126.0,
    220.0,
    201.0,
    283.0,
    145.0,
    195.0,
    156.0,
    365.0,
    273.0,
    206.0,
    330.0,
    273.0,
    151.0,
    303.0,
    271.0,
    234.0,
    219.0,
    267.0,
    353.0,
    138.0,
    205.0,
    129.0,
    176.0,
    166.0,
    208.0,
    275.0,
    120.0,
    199.0,
    175.0,
    230.0,
    135.0,
    257.0,
    393.0,
    134.0,
    113.0,
    190.0,
    128.0,
    152.0,
    141.0,
    168.0,
    136.0,
    177.0,
    203.0,
    185.0,
    164.0,
    284.0,
    207.0,
    224.0,
    149.0,
    182.0,
    171.0,
    221.0,
    253.0,
    311.0,
    357.0,
    206.0,
    251.0,
    295.0,
    280.0,
    500.0,
    289.0,
    253.0,
    500.0,
    343.0,
    423.0,
    292.0,
    500.0,
    434.0,
    265.0,
    365.0,
    500.0,
    500.0,
    457.0,
    291.0,
    400.0,
    459.0,
    500.0,
    500.0,
    500.0,
    368.0,
    427.0,
    280.0,
    495.0,
    500.0,
    500.0,
    500.0,
    500.0,
    500.0,
    500.0,
    500.0,
    500.0,
    394.0,
    500.0,
    500.0,
    500.0,
    500.0,
    500.0,
    500.0,
    500.0,
    500.0,
    500.0,
    500.0,
    500.0,
    500.0,
    500.0,
    500.0,
    500.0,
    500.0,
    500.0,
    500.0,
    500.0,
    500.0,
    500.0,
    500.0,
    500.0,
    500.0,
    500.0,
    500.0,
    500.0,
    500.0,
    500.0,
    500.0,
    500.0,
    500.0,
    500.0,
    500.0,
    500.0,
    500.0,
    500.0,
    500.0,
    500.0,
    500.0,
    500.0,
    500.0,
    500.0,
    500.0,
    500.0,
    500.0,
    500.0,
    500.0,
    500.0,
    500.0,
    500.0,
    500.0,
    500.0,
    500.0,
    500.0,
    500.0,
    500.0,
    500.0,
    500.0,
    500.0,
    500.0,
    500.0,
    500.0,
    500.0,
    500.0,
    500.0,
    500.0,
    500.0,
    500.0,
    500.0,
    500.0,
    500.0,
    500.0,
    500.0,
    500.0,
    500.0,
    500.0,
    500.0,
    500.0,
    500.0,
    500.0,
    500.0,
    500.0,
    500.0,
    500.0,
    500.0,
    500.0,
    500.0,
    500.0,
    500.0,
    500.0,
    500.0,
    500.0,
    500.0,
    500.0,
    500.0,
    500.0,
    500.0,
    500.0,
    500.0
  ],
  "moving_avg_100": [
    22.0,
    19.0,
    20.333333333333332,
    18.75,
    19.6,
    22.5,
    21.714285714285715,
    22.625,
    22.11111111111111,
    21.5,
    21.272727272727273,
    21.916666666666668,
    21.307692307692307,
    20.571428571428573,
    19.733333333333334,
    19.625,
    19.705882352941178,
    19.944444444444443,
    20.94736842105263,
    20.9,
    20.761904761904763,
    20.818181818181817,
    20.434782608695652,
    20.083333333333332,
    19.84,
    19.692307692307693,
    19.444444444444443,
    19.25,
    19.17241379310345,
    19.433333333333334,
    19.161290322580644,
    19.0625,
    19.03030303030303,
    18.852941176470587,
    18.857142857142858,
    19.22222222222222,
    19.35135135135135,
    19.13157894736842,
    19.641025641025642,
    19.625,
    19.51219512195122,
    19.714285714285715,
    19.697674418604652,
    19.704545454545453,
    19.533333333333335,
    19.5,
    19.4468085106383,
    19.5625,
    19.653061224489797,
    19.7,
    19.58823529411765,
    19.46153846153846,
    19.264150943396228,
    19.59259259259259,
    19.527272727272727,
    19.375,
    19.24561403508772,
    19.689655172413794,
    19.677966101694917,
    19.633333333333333,
    19.75409836065574,
    19.822580645161292,
    19.873015873015873,
    19.796875,
    19.8,
    19.71212121212121,
    19.70149253731343,
    19.602941176470587,
    20.52173913043478,
    20.485714285714284,
    20.422535211267604,
    20.59722222222222,
    20.643835616438356,
    20.68918918918919,
    20.546666666666667,
    20.513157894736842,
    20.87012987012987,
    20.794871794871796,
    20.924050632911392,
    20.85,
    20.765432098765434,
    20.829268292682926,
    20.710843373493976,
    20.654761904761905,
    20.764705882352942,
    20.72093023255814,
    20.620689655172413,
    20.568181818181817,
    20.674157303370787,
    20.555555555555557,
    20.53846153846154,
    20.543478260869566,
    20.451612903225808,
    20.606382978723403,
    20.621052631578948,
    20.84375,
    20.762886597938145,
    20.908163265306122,
    21.09090909090909,
    21.23,
    21.44,
    21.49,
    21.42,
    21.45,
    21.34,
    21.29,
    21.28,
    21.14,
    21.42,
    21.43,
    21.55,
    21.46,
    21.48,
    21.8,
    21.94,
    22.05,
    21.98,
    21.98,
    21.74,
    21.7,
    21.74,
    21.64,
    22.01,
    22.02,
    22.05,
    22.09,
    22.12,
    22.3,
    22.31,
    22.41,
    22.53,
    22.5,
    22.47,
    22.78,
    22.75,
    22.55,
    22.45,
    22.57,
    22.32,
    22.24,
    22.27,
    22.38,
    22.54,
    22.55,
    22.65,
    22.86,
    23.11,
    23.12,
    23.49,
    23.59,
    24.45,
    24.5,
    24.93,
    24.71,
    24.8,
    24.97,
    25.2,
    25.38,
    25.4,
    25.42,
    25.44,
    25.49,
    25.47,
    25.59,
    25.62,
    25.63,
    25.54,
    25.74,
    25.03,
    25.23,
    25.29,
    25.32,
    25.28,
    25.57,
    26.14,
    26.43,
    26.17,
    26.18,
    26.21,
    27.12,
    27.29,
    27.22,
    27.69,
    27.9,
    28.68,
    29.14,
    29.27,
    29.28,
    29.12,
    29.33,
    29.31,
    29.36,
    29.86,
    29.79,
    30.28,
    30.04,
    30.03,
    29.85,
    29.81,
    29.63,
    30.04,
    30.53,
    30.62,
    31.23,
    31.42,
    31.29,
    31.41,
    31.5,
    31.88,
    31.93,
    32.65,
    32.58,
    32.62,
    32.36,
    32.53,
    33.67,
    34.08,
    34.07,
    34.04,
    34.64,
    34.72,
    34.95,
    34.72,
    34.78,
    35.41,
    35.49,
    35.7,
    36.85,
    37.07,
    37.0,
    37.75,
    38.09,
    38.23,
    38.05,
    38.64,
    38.8,
    39.38,
    40.31,
    40.81,
    41.0,
    41.27,
    41.54,
    41.77,
    41.78,
    42.55,
    42.78,
    42.86,
    42.73,
    42.76,
    42.97,
    42.56,
    42.53,
    42.59,
    43.2,
    43.39,
    43.42,
    43.97,
    43.97,
    44.1,
    44.05,
    45.26,
    47.34,
    48.15,
    49.05,
    49.65,
    50.79,
    51.79,
    53.55,
    54.71,
    56.2,
    56.58,
    56.98,
    57.95,
    57.69,
    58.2,
    59.31,
    61.08,
    63.82,
    64.54,
    64.22,
    65.33,
    67.54,
    67.61,
    69.09,
    69.06,
    70.38,
    71.92,
    73.1,
    74.22,
    76.11,
    77.95,
    80.52,
    81.35,
    83.02,
    83.87,
    87.34,
    89.95,
    91.84,
    94.79,
    97.35,
    98.02,
    100.35,
    102.81,
    104.37,
    106.25,
    108.73,
    111.98,
    113.12,
    114.33,
    115.4,
    116.13,
    117.66,
    119.54,
    122.12,
    122.93,
    123.49,
    124.69,
    126.76,
    127.99,
    129.8,
    133.43,
    134.42,
    135.29,
    137.0,
    137.48,
    138.72,
    139.76,
    139.97,
    140.93,
    142.4,
    143.45,
    144.83,
    146.18,
    148.76,
    150.08,
    152.04,
    152.81,
    153.47,
    154.54,
    156.45,
    158.53,
    160.98,
    163.97,
    165.81,
    167.33,
    169.66,
    171.96,
    176.83,
    179.08,
    181.08,
    185.49,
    188.77,
    192.42,
    194.58,
    199.14,
    203.17,
    204.92,
    207.94,
    212.6,
    217.46,
    220.53,
    221.07,
    224.05,
    227.47,
    231.64,
    235.35,
    239.25,
    240.84,
    243.83,
    244.76,
    249.11,
    253.35,
    257.18,
    261.91,
    265.73,
    269.15,
    272.16,
    274.26,
    278.2,
    281.4,
    284.98,
    287.58,
    291.93,
    295.08,
    299.03,
    302.08,
    305.29,
    308.94,
    312.68,
    315.48,
    318.47,
    320.64,
    324.19,
    327.24,
    330.68,
    332.03,
    334.3,
    337.24,
    338.94,
    341.21,
    344.7,
    346.67,
    348.96,
    351.62,
    354.43,
    356.76,
    358.23,
    361.85,
    364.8,
    368.51,
    371.75,
    375.09,
    378.01,
    380.26,
    384.06,
    387.07,
    390.32,
    393.02,
    396.67,
    399.1,
    400.17,
    403.83,
    407.7,
    410.8,
    414.52,
    418.0,
    421.59,
    424.91,
    428.55,
    431.78,
    434.75,
    437.9,
    441.26,
    443.42,
    446.35,
    449.11,
    452.62,
    455.8,
    459.09,
    461.88,
    464.35,
    466.24,
    467.67,
    470.61,
    473.1,
    475.15,
    477.35,
    477.35,
    479.46,
    481.93,
    481.93,
    483.5,
    484.27,
    486.35,
    486.35,
    487.01,
    489.36,
    490.71,
    490.71,
    490.71,
    491.14,
    493.23,
    494.23,
    494.64,
    494.64,
    494.64,
    494.64,
    495.96,
    496.69,
    498.89,
    498.94,
    498.94,
    498.94,
    498.94,
    498.94,
    498.94,
    498.94,
    498.94,
    498.94,
    500.0
  ],
  "metrics": {
    "episode": [
      98,
      175,
      224,
      261,
      277,
      290,
      299,
      307,
      318,
      329,
      339,
      347,
      353,
      358,
      363,
      367,
      372,
      376,
      380,
      385,
      389,
      393,
      397,
      401,
      405,
      409,
      413,
      417,
      421,
      425,
      430,
      434,
      438,
      442,
      446,
      450,
      454,
      458,
      462,
      466,
      471,
      475,
      479,
      480
    ],
    "update": [
      1,
      2,
      3,
      4,
      5,
      6,
      7,
      8,
      9,
      10,
      11,
      12,
      13,
      14,
      15,
      16,
      17,
      18,
      19,
      20,
      21,
      22,
      23,
      24,
      25,
      26,
      27,
      28,
      29,
      30,
      31,
      32,
      33,
      34,
      35,
      36,
      37,
      38,
      39,
      40,
      41,
      42,
      43,
      44
    ],
    "value_loss": [
      62.05442005395889,
      46.847192883491516,
      69.66796320676804,
      75.61077205113003,
      88.43956804275513,
      72.40015703439713,
      58.206907749176025,
      41.53141447901726,
      16.935920745134354,
      18.205268993973732,
      12.026002008087781,
      13.69356581568718,
      42.23471626639366,
      54.391298085451126,
      75.2672698199749,
      49.60066756606102,
      23.39490845799446,
      75.79846452176571,
      63.68265114724636,
      132.31744956970215,
      119.16759604215622,
      116.38894861936569,
      123.1387750506401,
      92.51703760027885,
      130.39001059532166,
      124.7999986410141,
      125.81468299031258,
      119.06390641629696,
      106.29354619979858,
      112.93445813655853,
      109.63123252987862,
      104.92931070923805,
      119.63952326774597,
      125.6926660835743,
      128.56506752967834,
      118.87646654248238,
      122.70320570468903,
      128.73075491189957,
      128.1529051065445,
      124.0375404059887,
      139.86262571811676,
      124.63907688856125,
      120.63198530673981,
      136.69452244894845
    ],
    "explained_variance": [
      0.20218682289123535,
      0.39511603116989136,
      0.3344372510910034,
      0.3808240294456482,
      0.5688731670379639,
      0.6809563636779785,
      0.823189914226532,
      0.8976601958274841,
      0.9866417050361633,
      0.9847875237464905,
      0.9897846579551697,
      0.9841839671134949,
      0.9126866459846497,
      0.9202417731285095,
      0.868072509765625,
      0.9376882910728455,
      0.9746924638748169,
      0.7310674786567688,
      0.7635790705680847,
      0.25762635469436646,
      0.1257917881011963,
      0.19937562942504883,
      0.07465600967407227,
      0.44574248790740967,
      -0.010335564613342285,
      0.03699016571044922,
      0.00508648157119751,
      0.07263219356536865,
      0.20358747243881226,
      0.11304771900177002,
      0.2009878158569336,
      0.2534549832344055,
      0.08606219291687012,
      0.04426109790802002,
      0.012330412864685059,
      0.08397310972213745,
      0.08690088987350464,
      0.05930298566818237,
      0.007485806941986084,
      0.018489420413970947,
      0.10602819919586182,
      0.0252000093460083,
      0.0010329484939575195,
      0.028751015663146973
    ],
    "approx_kl": [
      0.008524658354872372,
      0.0050522187375463545,
      0.011279063841357129,
      0.007930768547313553,
      0.004597762275807327,
      0.009613004884158727,
      0.001924857289850479,
      0.004299212865589652,
      0.0056304305253433995,
      0.005341387488442706,
      0.007519009879467135,
      0.0025063980647246353,
      0.001483389252825873,
      0.0024665579039719887,
      0.0011534206350916065,
      0.0023952346564328764,
      0.003846088791760849,
      0.0032495560772076715,
      0.006370002338371705,
      0.0017747346864780411,
      0.004557462452794425,
      0.003583462443202734,
      0.003640496634034207,
      0.0027969308212050237,
      0.0016111159784486517,
      0.0003976892039645463,
      0.002871622720704181,
      0.002436905386275612,
      0.0022644643468083814,
      0.0006369161674228963,
      0.002008648072660435,
      0.001644670199311804,
      0.0012722720566671342,
      0.003255419018387329,
      0.003333148364617955,
      0.0028181345369375776,
      0.003247020940762013,
      0.0035327522018633317,
      0.000386491807148559,
      0.002444735040626256,
      0.0006804224140068982,
      0.0009246890040230937,
      0.0038066480847191997,
      0.0011831955790902221
    ],
    "policy_loss": [
      -0.01810184849455254,
      -0.011010947862814646,
      -0.0192708136382862,
      -0.005348747689276933,
      -0.004985330015188083,
      -0.003746009402675554,
      -0.004313703037041705,
      -0.014242568300687708,
      0.0007658869435545057,
      -0.005005475195503095,
      -0.008997204884582636,
      -0.004682625876739621,
      -0.028639031981583685,
      -0.02042484047706239,
      -0.02250107300642412,
      -0.02059200323128607,
      -0.012304797979595605,
      -0.025471906090388075,
      -0.027803283162938897,
      -0.01630802765430417,
      -0.020904176053591073,
      -0.021577026265731547,
      -0.017725955054629594,
      -0.02123204222880304,
      -0.019165425386745483,
      -0.018546725928899832,
      -0.01957458004471846,
      -0.019921619103115518,
      -0.020042656440637074,
      -0.01856343103281688,
      -0.018961529392981902,
      -0.020571042587107513,
      -0.01921922974725021,
      -0.01992277058889158,
      -0.020494262273132335,
      -0.02006357174832374,
      -0.020984052236599382,
      -0.02073971701611299,
      -0.019323152337165084,
      -0.02027242617623415,
      -0.012279078000574373,
      -0.01761894165247213,
      -0.020587190811056644,
      -0.0186925580991166
    ],
    "entropy": [
      0.6848816489800811,
      0.6761982282623649,
      0.6409486867487431,
      0.6262151053973607,
      0.5925419069826603,
      0.557786462828517,
      0.5600188942626119,
      0.555129730142653,
      0.5629951767623425,
      0.5579768093302846,
      0.5674581089798285,
      0.5519176861271262,
      0.5666218651458621,
      0.5606955755501986,
      0.5486237034201622,
      0.5538186524063349,
      0.5475436970591545,
      0.5534157259389758,
      0.5382535429671407,
      0.5509325293824077,
      0.5567303830757737,
      0.5348396580666304,
      0.5333457728847861,
      0.5370354242622852,
      0.5553444623947144,
      0.5398685969412327,
      0.5386349717155099,
      0.5378733044490218,
      0.5247162845917046,
      0.5148374158889055,
      0.5072718877345324,
      0.5195186887867749,
      0.4995533158071339,
      0.5050120837986469,
      0.517042763531208,
      0.5014637722633779,
      0.5119192488491535,
      0.5011460045352578,
      0.5189037383534014,
      0.5236239666119218,
      0.5170271694660187,
      0.5048167798668146,
      0.49531844817101955,
      0.49535958788224627
    ],
    "clip_fraction": [
      0.1282958984375,
      0.0506591796875,
      0.1376953125,
      0.06763392857142857,
      0.047119140625,
      0.1173095703125,
      0.012451171875,
      0.03759765625,
      0.0726318359375,
      0.072021484375,
      0.1018813775510204,
      0.017333984375,
      0.01025390625,
      0.01611328125,
      0.0068359375,
      0.017822265625,
      0.041015625,
      0.0411376953125,
      0.0804443359375,
      0.019287109375,
      0.05419921875,
      0.0347900390625,
      0.02685546875,
      0.0135498046875,
      0.0164794921875,
      0.000244140625,
      0.0260009765625,
      0.020263671875,
      0.017578125,
      0.0,
      0.0130615234375,
      0.01513671875,
      0.0093994140625,
      0.0322265625,
      0.0384521484375,
      0.0218505859375,
      0.0347900390625,
      0.0340576171875,
      0.0001220703125,
      0.0208740234375,
      0.0013427734375,
      0.00634765625,
      0.0369873046875,
      0.007021103885823062
    ]
  },
  "config": {
    "max_episodes": 600,
    "rollout_steps": 2048,
    "lr": 0.001,
    "K_epochs": 4,
    "batch_size": 128,
    "gamma": 0.99,
    "gae_lambda": 0.95,
    "eps_clip": 0.2,
    "value_coef": 0.5,
    "entropy_coef": 0.01,
    "target_reward": 500.0,
    "patience": 150,
    "min_episodes": 100,
    "target_kl": 0.03,
    "eval_deterministic": true
  },
  "evaluation": {
    "episodes": 20,
    "mode": "deterministic",
    "mean_reward": 500.0,
    "std_reward": 0.0,
    "rewards": [
      500.0,
      500.0,
      500.0,
      500.0,
      500.0,
      500.0,
      500.0,
      500.0,
      500.0,
      500.0,
      500.0,
      500.0,
      500.0,
      500.0,
      500.0,
      500.0,
      500.0,
      500.0,
      500.0,
      500.0
    ]
  },
  "evaluation_comparison": {
    "deterministic": {
      "episodes": 10,
      "mode": "deterministic",
      "mean_reward": 500.0,
      "std_reward": 0.0,
      "rewards": [
        500.0,
        500.0,
        500.0,
        500.0,
        500.0,
        500.0,
        500.0,
        500.0,
        500.0,
        500.0
      ]
    },
    "stochastic": {
      "episodes": 10,
      "mode": "stochastic",
      "mean_reward": 500.0,
      "std_reward": 0.0,
      "rewards": [
        500.0,
        500.0,
        500.0,
        500.0,
        500.0,
        500.0,
        500.0,
        500.0,
        500.0,
        500.0
      ]
    }
  }
}